MANIFEST.in
README.md
requirements.txt
setup.py
wagtail_block_collection/__init__.py
wagtail_block_collection/blocks.py
wagtail_block_collection/fields.py
wagtail_block_collection/models.py
wagtail_block_collection.egg-info/PKG-INFO
wagtail_block_collection.egg-info/SOURCES.txt
wagtail_block_collection.egg-info/dependency_links.txt
wagtail_block_collection.egg-info/requires.txt
wagtail_block_collection.egg-info/top_level.txt
wagtail_block_collection/migrations/0001_initial.py
wagtail_block_collection/migrations/__init__.py
wagtail_block_collection/static/wagtail_block_collection/css/sections.css
wagtail_block_collection/static/wagtail_block_collection/css/slider.css
wagtail_block_collection/static/wagtail_block_collection/js/countdown.js
wagtail_block_collection/static/wagtail_block_collection/js/typewriter.js
wagtail_block_collection/templates/wagtail_block_collection/card_deck_block.html
wagtail_block_collection/templates/wagtail_block_collection/basic/button_block.html
wagtail_block_collection/templates/wagtail_block_collection/basic/icon_block.html
wagtail_block_collection/templates/wagtail_block_collection/basic/line_block.html
wagtail_block_collection/templates/wagtail_block_collection/basic/text_and_image_block.html
wagtail_block_collection/templates/wagtail_block_collection/basic/text_block.html
wagtail_block_collection/templates/wagtail_block_collection/basic/title_block.html
wagtail_block_collection/templates/wagtail_block_collection/layout/accordion.html
wagtail_block_collection/templates/wagtail_block_collection/layout/collapse_button.html
wagtail_block_collection/templates/wagtail_block_collection/layout/row.html
wagtail_block_collection/templates/wagtail_block_collection/layout/spacer_block.html
wagtail_block_collection/templates/wagtail_block_collection/media/image_slider_block.html
wagtail_block_collection/templates/wagtail_block_collection/media/img_block.html
wagtail_block_collection/templates/wagtail_block_collection/media/youtube_video_block.html
wagtail_block_collection/templates/wagtail_block_collection/miscellaneous/google_maps.html
wagtail_block_collection/templates/wagtail_block_collection/sections/basic_section.html
