Metadata-Version: 2.1
Name: wagtail-block-collection
Version: 0.0.5
Summary: A Collection of wagtail steam fields
Home-page: https://github.com/slice-of-bits/wagtail-block-collection
Author: SliceOfBits
Author-email: matthijs@sliceofbits.com
License: MIT
Keywords: WAGTAIL,STREAMFIELD,WAGTAIL_BLOCKS,WAGTAIL CMS
Platform: UNKNOWN
Classifier: Development Status :: 4 - Beta
Classifier: Environment :: Web Environment
Classifier: Framework :: Django
Classifier: Framework :: Wagtail
Classifier: Intended Audience :: Developers
Classifier: License :: OSI Approved :: MIT License
Classifier: Operating System :: OS Independent
Classifier: Programming Language :: Python
Classifier: Programming Language :: Python :: 3.6
Classifier: Programming Language :: Python :: 3.7
Classifier: Programming Language :: Python :: 3.8
Classifier: Topic :: Internet :: WWW/HTTP
Classifier: Topic :: Internet :: WWW/HTTP :: Dynamic Content
Classifier: Topic :: Software Development
Provides-Extra: testing
Provides-Extra: docs
